{
  "id": 1,
  "name": "Director Dramatique",
  "note": "Wasteland Theater Troupe Quest NPC",
  "pages": [
    {
      "conditions": {
        "actorId": 1,
        "actorValid": false,
        "itemId": 1,
        "itemValid": false,
        "selfSwitchCh": "A",
        "selfSwitchValid": false,
        "switch1Id": 1,
        "switch1Valid": false,
        "switch2Id": 1,
        "switch2Valid": false,
        "variableId": 1,
        "variableValid": false,
        "variableValue": 0
      },
      "directionFix": false,
      "image": {
        "characterIndex": 6,
        "characterName": "Actor3",
        "direction": 2,
        "pattern": 1,
        "tileId": 0
      },
      "list": [
        {
          "code": 101,
          "indent": 0,
          "parameters": [
            "Actor3",
            6,
            0,
            2,
            "Director Dramatique"
          ]
        },
        {
          "code": 401,
          "indent": 0,
          "parameters": [
            "Darling! You have such presence! I am Director Dramatique of the Wasteland Players."
          ]
        },
        {
          "code": 401,
          "indent": 0,
          "parameters": [
            "We travel the wasteland performing classics and new works about our current reality."
          ]
        },
        {
          "code": 401,
          "indent": 0,
          "parameters": [
            "Art must survive! Culture must endure! Even in these dark times, people need stories!"
          ]
        },
        {
          "code": 401,
          "indent": 0,
          "parameters": [
            "We need protection, new performers, and help finding venues. Join our troupe?"
          ]
        },
        {
          "code": 0,
          "indent": 0,
          "parameters": []
        }
      ],
      "moveFrequency": 3,
      "moveRoute": {
        "list": [
          {
            "code": 0,
            "parameters": []
          }
        ],
        "repeat": true,
        "skippable": false,
        "wait": false
      },
      "moveSpeed": 3,
      "moveType": 0,
      "priorityType": 1,
      "stepAnime": false,
      "through": false,
      "trigger": 0,
      "walkAnime": true
    }
  ],
  "x": 15,
  "y": 10
}